easylcsc4kicad/__init__.py
easylcsc4kicad/cli.py
easylcsc4kicad/client.py
easylcsc4kicad/models.py
easylcsc4kicad/search.py
easylcsc4kicad/download/__init__.py
easylcsc4kicad/download/component.py
easylcsc4kicad/download/footprint.py
easylcsc4kicad/download/model3d.py
easylcsc4kicad/download/symbol.py
easylcsc4kicad-0.1.2.dist-info/METADATA
easylcsc4kicad-0.1.2.dist-info/WHEEL
easylcsc4kicad-0.1.2.dist-info/entry_points.txt
easylcsc4kicad-0.1.2.dist-info/RECORD
