Metadata-Version: 2.4
Name: easylcsc4kicad
Version: 0.1.2
Summary: Search LCSC and EasyEDA for schematics and footprints
Project-URL: Homepage, https://github.com/cypherpunksamurai/easylcsc4kicadz
Project-URL: Issues, https://github.com/cypherpunksamurai/easylcsc4kicadz/issues
Author: Rakesh Chowdhury
License-Expression: MIT
Classifier: Environment :: Console
Classifier: License :: OSI Approved :: MIT License
Classifier: Operating System :: OS Independent
Classifier: Programming Language :: Python :: 3.10
Classifier: Programming Language :: Python :: 3.11
Classifier: Programming Language :: Python :: 3.12
Classifier: Topic :: Scientific/Engineering :: Electronic Design Automation (EDA)
Requires-Python: >=3.10
Requires-Dist: kicadmodtree>=1.1.2
Requires-Dist: requests>=2.28
